README
setup.py
tclite/__init__.py
tclite/properties.py
tclite.egg-info/PKG-INFO
tclite.egg-info/SOURCES.txt
tclite.egg-info/dependency_links.txt
tclite.egg-info/top_level.txt