Metadata-Version: 1.0
Name: tclite
Version: 0.33
Summary: Object wrapper for tokyo cabinet / tokyo tyrant
Home-page: http://bitbucket.org/imbolc/tclite/
Author: Imbolc
Author-email: imbolc@imbolc.name
License: BSD
Keywords: tc,tokyo,cabinet,tyrant,nosql,orm,model,document,non-relational,document-oriented,key/value
Platform: UNKNOWN
Classifier: Development Status :: 4 - Beta
Classifier: License :: OSI Approved :: BSD License
Classifier: Operating System :: OS Independent
Classifier: Programming Language :: Python
Classifier: Topic :: Software Development :: Libraries :: Python Modules
